<?xml version="1.0" encoding="UTF-8"?>
<pmd-cpd>
<duplication lines="38" tokens="117">
<file line="55" path="/scratch/hudson/workspace/jclouds-1.5.0-beta.1-maven-site/labs/opsource-servers/src/main/java/org/jclouds/opsource/servers/domain/DeployedServer.java"/>
<file line="51" path="/scratch/hudson/workspace/jclouds-1.5.0-beta.1-maven-site/labs/opsource-servers/src/main/java/org/jclouds/opsource/servers/domain/PendingDeployServer.java"/>
<codefragment>
<![CDATA[
	  private Status status;
	  
      public Builder id(String id) {
    	  this.id = id;
    	  return this;
      }

      public Builder name(String name) {
    	  this.name = name;
    	  return this;
      }

      public Builder description(String description) {
    	  this.description = description;
    	  return this;
      }
      
      public Builder machineSpecification(MachineSpecification machineSpecification) {
    	  this.machineSpecification = machineSpecification;
    	  return this;
      }
      
      public Builder sourceImageId(String sourceImageId) {
    	  this.sourceImageId = sourceImageId;
    	  return this;
      }
      
      public Builder networkId(String networkId) {
    	  this.networkId = networkId;
    	  return this;
      }
      
      public Builder privateIpAddress(String privateIpAddress) {
    	  this.privateIpAddress = privateIpAddress;
    	  return this;
      }

      public Builder status(Status status) {
]]>
</codefragment>
</duplication>
<duplication lines="19" tokens="111">
<file line="129" path="/scratch/hudson/workspace/jclouds-1.5.0-beta.1-maven-site/labs/opsource-servers/src/main/java/org/jclouds/opsource/servers/domain/DeployedServer.java"/>
<file line="104" path="/scratch/hudson/workspace/jclouds-1.5.0-beta.1-maven-site/labs/opsource-servers/src/main/java/org/jclouds/opsource/servers/domain/PendingDeployServer.java"/>
<codefragment>
<![CDATA[
   private PendingDeployServer() {
      // For JAXB and builder use
   }

   @XmlElement(namespace = SERVER, name="id")
   private String id;
   @XmlElement(namespace = SERVER, name="name")
   private String name;
   @XmlElement(namespace = SERVER, name="description")
   private String description;
   @XmlElement(namespace = SERVER, name="machineSpecification")
   private MachineSpecification machineSpecification;
   @XmlElement(namespace = SERVER, name="sourceImageId")
   private String sourceImageId;
   @XmlElement(namespace = SERVER, name="networkId")
   private String networkId;
   @XmlElement(namespace = SERVER, name="privateIpAddress")
   private String privateIpAddress;
   @XmlElement(namespace = SERVER, name="status")
]]>
</codefragment>
</duplication>
</pmd-cpd>